LICENSE
MANIFEST.in
README.md
setup.py
Django_Youtuber.egg-info/PKG-INFO
Django_Youtuber.egg-info/SOURCES.txt
Django_Youtuber.egg-info/dependency_links.txt
Django_Youtuber.egg-info/requires.txt
Django_Youtuber.egg-info/top_level.txt
youtuber/__init__.py
youtuber/admin.py
youtuber/client.py
youtuber/exceptions.py
youtuber/models.py
youtuber/pipelines.py
youtuber/tasks.py
youtuber/utils.py
youtuber/management/__init__.py
youtuber/migrations/0001_initial.py
youtuber/migrations/__init__.py
youtuber/tests/__init__.py