Metadata-Version: 1.0
Name: Django-Youtuber
Version: 0.1.1
Summary: Django app for fetching videos from channels or playlists.
Home-page: https://github.com/rakanalh/django-youtuber
Author: Rakan Alhneiti
Author-email: rakan.alhneiti@gmail.com
License: LICENSE
Platform: UNKNOWN
